aytch/__init__.py
aytch/__version__.py
aytch/helper.py
aytch/main.py
aytch/utils.py
aytch-0.1.1.dist-info/LICENSE
aytch-0.1.1.dist-info/METADATA
aytch-0.1.1.dist-info/WHEEL
aytch-0.1.1.dist-info/RECORD
