Metadata-Version: 2.1
Name: aytch
Version: 0.1.1
Summary: Async YouTube Channels Info
Home-page: https://github.com/kieled/aytch
License: MIT
Keywords: scrapper,parser,info,aiohttp,channels,asyncio,yt,youtube,async
Author: Kiel Ed
Author-email: kieledssh@gmail.com
Requires-Python: >=3.8,<4.0
Classifier: Intended Audience :: Developers
Classifier: License :: OSI Approved :: Apache Software License
Classifier: License :: OSI Approved :: MIT License
Classifier: Programming Language :: Python
Classifier: Programming Language :: Python :: 3
Classifier: Programming Language :: Python :: 3.8
Classifier: Programming Language :: Python :: 3.9
Classifier: Programming Language :: Python :: 3.10
Classifier: Programming Language :: Python :: 3.11
Classifier: Programming Language :: Python :: 3.10
Classifier: Programming Language :: Python :: 3.11
Classifier: Programming Language :: Python :: 3.8
Classifier: Programming Language :: Python :: 3.9
Classifier: Programming Language :: Python :: Implementation :: PyPy
Classifier: Topic :: Software Development :: Libraries :: Python Modules
Requires-Dist: aiohttp (>=3.8.4,<4.0.0)
Project-URL: Repository, https://github.com/kieled/aytch
